pygurt/__init__.py
pygurt/client.py
pygurt/common.py
pygurt/py.typed
pygurt/server.py
pygurt-1.0.2.dist-info/METADATA
pygurt-1.0.2.dist-info/WHEEL
pygurt-1.0.2.dist-info/licenses/LICENSE.md
pygurt-1.0.2.dist-info/RECORD
