Metadata-Version: 2.4
Name: pygurt
Version: 1.0.2
Summary: A Python implementation of the GURT standard, including both a client and server!
Project-URL: Homepage, https://git.itoj.dev/pygurt
Project-URL: Repository, https://git.itoj.dev/pygurt
Project-URL: Issues, https://git.itoj.dev/pygurt/issues
Author-email: ItsThatOneJack <157112523+ItsThatOneJack-Dev@users.noreply.github.com>
License: AGPL-3.0
License-File: LICENSE.md
Classifier: Development Status :: 4 - Beta
Classifier: Intended Audience :: Developers
Classifier: License :: OSI Approved :: GNU Affero General Public License v3
Classifier: Natural Language :: English
Classifier: Operating System :: OS Independent
Classifier: Programming Language :: Python :: 3.11
Classifier: Programming Language :: Python :: 3.12
Classifier: Programming Language :: Python :: 3.13
Classifier: Programming Language :: Python :: 3.14
Classifier: Topic :: Security :: Cryptography
Requires-Python: >=3.12
Requires-Dist: rich>=14.1.0
